edc_dashboard/__init__.py
edc_dashboard/apps.py
edc_dashboard/auth_objects.py
edc_dashboard/auths.py
edc_dashboard/dashboard_templates.py
edc_dashboard/middleware.py
edc_dashboard/models.py
edc_dashboard/navbars.py
edc_dashboard/system_checks.py
edc_dashboard/url_config.py
edc_dashboard/url_names.py
edc_dashboard/urls.py
edc_dashboard/utils.py
edc_dashboard/locale/sw/LC_MESSAGES/django.mo
edc_dashboard/locale/sw/LC_MESSAGES/django.po
edc_dashboard/management/__init__.py
edc_dashboard/management/commands/__init__.py
edc_dashboard/management/commands/update_search_slugs.py
edc_dashboard/migrations/0001_initial.py
edc_dashboard/migrations/0002_auto_20220910_0214.py
edc_dashboard/migrations/0003_alter_edcpermissions_device_created_and_more.py
edc_dashboard/migrations/0004_edcpermissions_locale_created_and_more.py
edc_dashboard/migrations/__init__.py
edc_dashboard/static/.DS_Store
edc_dashboard/static/edc_dashboard/css/.DS_Store
edc_dashboard/static/edc_dashboard/css/changelist_button.css
edc_dashboard/static/edc_dashboard/css/edc.css
edc_dashboard/static/edc_dashboard/css/sticky-footer-navbar.css
edc_dashboard/static/edc_dashboard/icons/apple-touch-icon-114x114.png
edc_dashboard/static/edc_dashboard/icons/apple-touch-icon-120x120.png
edc_dashboard/static/edc_dashboard/icons/apple-touch-icon-144x144.png
edc_dashboard/static/edc_dashboard/icons/apple-touch-icon-152x152.png
edc_dashboard/static/edc_dashboard/icons/apple-touch-icon-180x180.png
edc_dashboard/static/edc_dashboard/icons/apple-touch-icon-57x57.png
edc_dashboard/static/edc_dashboard/icons/apple-touch-icon-72x72.png
edc_dashboard/static/edc_dashboard/icons/apple-touch-icon-76x76.png
edc_dashboard/static/edc_dashboard/icons/apple-touch-icon.png
edc_dashboard/static/edc_dashboard/icons/favicon.ico
edc_dashboard/static/edc_dashboard/js/edc.js
edc_dashboard/static/edc_dashboard/js/ie10-viewport-bug-workaround.js
edc_dashboard/templates/403.html
edc_dashboard/templates/403_csrf.html
edc_dashboard/templates/404.html
edc_dashboard-1.0.3.dist-info/licenses/AUTHORS.rst
edc_dashboard-1.0.3.dist-info/licenses/LICENSE
edc_dashboard-1.0.3.dist-info/METADATA
edc_dashboard-1.0.3.dist-info/WHEEL
edc_dashboard-1.0.3.dist-info/top_level.txt
edc_dashboard-1.0.3.dist-info/RECORD
